cert_human_py3/__init__.py
cert_human_py3-1.0.0.dist-info/LICENSE
cert_human_py3-1.0.0.dist-info/WHEEL
cert_human_py3-1.0.0.dist-info/METADATA
cert_human_py3-1.0.0.dist-info/RECORD
