Metadata-Version: 2.1
Name: cert-human-py3
Version: 1.0.0
Summary: 
License: MIT
Author: dev
Author-email: dev@qiyutech.tech
Requires-Python: >=3.9,<4.0
Classifier: License :: OSI Approved :: MIT License
Classifier: Programming Language :: Python :: 3
Classifier: Programming Language :: Python :: 3.9
Requires-Dist: asn1crypto (>=1.4,<2.0)
Requires-Dist: pyOpenSSL (>=20,<21)
